<?xml version="1.0"?>
<measure>
  <schema_version>3.0</schema_version>
  <error>wrong number of arguments (given 1, expected 0)</error>
  <name>cte_informe_dbhe</name>
  <uid>fda88851-76a7-48cb-8cbd-d0d6f803b8e5</uid>
  <version_id>9757b16c-1a95-4e57-bed3-87437970de63</version_id>
  <version_modified>20230421T115044Z</version_modified>
  <xml_checksum>72C8354A</xml_checksum>
  <class_name>CTE_InformeDBHE</class_name>
  <display_name> Informe DBHE</display_name>
  <description>Informe de resultados con informacion relativa al CTE DB-HE.</description>
  <modeler_description>Datos obtenidos de los resultados de EnergyPlus y del modelo de OpenStudio.
 La estructura del informe usa Bootstrap, y dimple js para las graficas.</modeler_description>
  <arguments>
    <argument>
      <name>mediciones_de_superficies_segun_CTE</name>
      <display_name>Mediciones de superficies segun CTE</display_name>
      <description></description>
      <type>Boolean</type>
      <units></units>
      <required>true</required>
      <model_dependent>false</model_dependent>
      <default_value>true</default_value>
      <choices>
        <choice>
          <value>true</value>
          <display_name>true</display_name>
        </choice>
        <choice>
          <value>false</value>
          <display_name>false</display_name>
        </choice>
      </choices>
      <min_value></min_value>
      <max_value></max_value>
    </argument>
    <argument>
      <name>demandas_por_componentes</name>
      <display_name>Demandas por componentes</display_name>
      <description></description>
      <type>Boolean</type>
      <units></units>
      <required>true</required>
      <model_dependent>false</model_dependent>
      <default_value>true</default_value>
      <choices>
        <choice>
          <value>true</value>
          <display_name>true</display_name>
        </choice>
        <choice>
          <value>false</value>
          <display_name>false</display_name>
        </choice>
      </choices>
      <min_value></min_value>
      <max_value></max_value>
    </argument>
    <argument>
      <name>annual_overview_section</name>
      <display_name>Resumen anual</display_name>
      <description></description>
      <type>Boolean</type>
      <units></units>
      <required>true</required>
      <model_dependent>false</model_dependent>
      <default_value>true</default_value>
      <choices>
        <choice>
          <value>true</value>
          <display_name>true</display_name>
        </choice>
        <choice>
          <value>false</value>
          <display_name>false</display_name>
        </choice>
      </choices>
      <min_value></min_value>
      <max_value></max_value>
    </argument>
    <argument>
      <name>building_summary_section</name>
      <display_name>Resumen del Modelo (Building summary section)</display_name>
      <description></description>
      <type>Boolean</type>
      <units></units>
      <required>true</required>
      <model_dependent>false</model_dependent>
      <default_value>true</default_value>
      <choices>
        <choice>
          <value>true</value>
          <display_name>true</display_name>
        </choice>
        <choice>
          <value>false</value>
          <display_name>false</display_name>
        </choice>
      </choices>
      <min_value></min_value>
      <max_value></max_value>
    </argument>
    <argument>
      <name>mediciones_envolvente</name>
      <display_name>Mediciones de la envolvente</display_name>
      <description></description>
      <type>Boolean</type>
      <units></units>
      <required>true</required>
      <model_dependent>false</model_dependent>
      <default_value>true</default_value>
      <choices>
        <choice>
          <value>true</value>
          <display_name>true</display_name>
        </choice>
        <choice>
          <value>false</value>
          <display_name>false</display_name>
        </choice>
      </choices>
      <min_value></min_value>
      <max_value></max_value>
    </argument>
    <argument>
      <name>cte_envelope_section_section</name>
      <display_name>Envelope</display_name>
      <description></description>
      <type>Boolean</type>
      <units></units>
      <required>true</required>
      <model_dependent>false</model_dependent>
      <default_value>true</default_value>
      <choices>
        <choice>
          <value>true</value>
          <display_name>true</display_name>
        </choice>
        <choice>
          <value>false</value>
          <display_name>false</display_name>
        </choice>
      </choices>
      <min_value></min_value>
      <max_value></max_value>
    </argument>
    <argument>
      <name>space_type_breakdown_section</name>
      <display_name>Space Type Breakdown</display_name>
      <description></description>
      <type>Boolean</type>
      <units></units>
      <required>true</required>
      <model_dependent>false</model_dependent>
      <default_value>true</default_value>
      <choices>
        <choice>
          <value>true</value>
          <display_name>true</display_name>
        </choice>
        <choice>
          <value>false</value>
          <display_name>false</display_name>
        </choice>
      </choices>
      <min_value></min_value>
      <max_value></max_value>
    </argument>
    <argument>
      <name>space_type_details_section</name>
      <display_name>Space Type Summary</display_name>
      <description></description>
      <type>Boolean</type>
      <units></units>
      <required>true</required>
      <model_dependent>false</model_dependent>
      <default_value>true</default_value>
      <choices>
        <choice>
          <value>true</value>
          <display_name>true</display_name>
        </choice>
        <choice>
          <value>false</value>
          <display_name>false</display_name>
        </choice>
      </choices>
      <min_value></min_value>
      <max_value></max_value>
    </argument>
    <argument>
      <name>zone_summary_section</name>
      <display_name>Zone Overview</display_name>
      <description></description>
      <type>Boolean</type>
      <units></units>
      <required>true</required>
      <model_dependent>false</model_dependent>
      <default_value>true</default_value>
      <choices>
        <choice>
          <value>true</value>
          <display_name>true</display_name>
        </choice>
        <choice>
          <value>false</value>
          <display_name>false</display_name>
        </choice>
      </choices>
      <min_value></min_value>
      <max_value></max_value>
    </argument>
    <argument>
      <name>cte_outdoor_air_section</name>
      <display_name>Aire exterior</display_name>
      <description></description>
      <type>Boolean</type>
      <units></units>
      <required>true</required>
      <model_dependent>false</model_dependent>
      <default_value>true</default_value>
      <choices>
        <choice>
          <value>true</value>
          <display_name>true</display_name>
        </choice>
        <choice>
          <value>false</value>
          <display_name>false</display_name>
        </choice>
      </choices>
      <min_value></min_value>
      <max_value></max_value>
    </argument>
    <argument>
      <name>source_energy_section</name>
      <display_name>Site and Source Summary</display_name>
      <description></description>
      <type>Boolean</type>
      <units></units>
      <required>true</required>
      <model_dependent>false</model_dependent>
      <default_value>true</default_value>
      <choices>
        <choice>
          <value>true</value>
          <display_name>true</display_name>
        </choice>
        <choice>
          <value>false</value>
          <display_name>false</display_name>
        </choice>
      </choices>
      <min_value></min_value>
      <max_value></max_value>
    </argument>
  </arguments>
  <outputs />
  <provenances />
  <tags>
    <tag>Reporting.QAQC</tag>
  </tags>
  <attributes>
    <attribute>
      <name>Uses SketchUp API</name>
      <value>false</value>
      <datatype>boolean</datatype>
    </attribute>
    <attribute>
      <name>Intended Software Tool</name>
      <value>OpenStudio Application</value>
      <datatype>string</datatype>
    </attribute>
    <attribute>
      <name>Intended Software Tool</name>
      <value>Parametric Analysis Tool</value>
      <datatype>string</datatype>
    </attribute>
    <attribute>
      <name>Intended Software Tool</name>
      <value>Analysis Spreadsheet</value>
      <datatype>string</datatype>
    </attribute>
    <attribute>
      <name>Intended Use Case</name>
      <value>Automatic Report Generation</value>
      <datatype>string</datatype>
    </attribute>
    <attribute>
      <name>Intended Software Tool</name>
      <value>OpenStudio Application</value>
      <datatype>string</datatype>
    </attribute>
    <attribute>
      <name>Intended Software Tool</name>
      <value>Parametric Analysis Tool</value>
      <datatype>string</datatype>
    </attribute>
    <attribute>
      <name>Intended Software Tool</name>
      <value>Analysis Spreadsheet</value>
      <datatype>string</datatype>
    </attribute>
    <attribute>
      <name>Intended Use Case</name>
      <value>Automatic Report Generation</value>
      <datatype>string</datatype>
    </attribute>
    <attribute>
      <name>Measure Type</name>
      <value>ReportingMeasure</value>
      <datatype>string</datatype>
    </attribute>
    <attribute>
      <name>Intended Software Tool</name>
      <value>OpenStudio Application</value>
      <datatype>string</datatype>
    </attribute>
    <attribute>
      <name>Intended Software Tool</name>
      <value>Parametric Analysis Tool</value>
      <datatype>string</datatype>
    </attribute>
    <attribute>
      <name>Intended Software Tool</name>
      <value>Analysis Spreadsheet</value>
      <datatype>string</datatype>
    </attribute>
    <attribute>
      <name>Intended Use Case</name>
      <value>Automatic Report Generation</value>
      <datatype>string</datatype>
    </attribute>
  </attributes>
  <files>
    <file>
      <filename>cte_query.rb</filename>
      <filetype>rb</filetype>
      <usage_type>resource</usage_type>
      <checksum>6DCFAC26</checksum>
    </file>
    <file>
      <filename>report.html.erb</filename>
      <filetype>erb</filetype>
      <usage_type>resource</usage_type>
      <checksum>04458219</checksum>
    </file>
    <file>
      <version>
        <software_program>OpenStudio</software_program>
        <identifier>1.7.5</identifier>
        <min_compatible>1.7.5</min_compatible>
      </version>
      <filename>measure.rb</filename>
      <filetype>rb</filetype>
      <usage_type>script</usage_type>
      <checksum>95C12082</checksum>
    </file>
    <file>
      <filename>out.idf</filename>
      <filetype>idf</filetype>
      <usage_type>test</usage_type>
      <checksum>2E62FF4C</checksum>
    </file>
    <file>
      <filename>test_InformeDBHE.rb</filename>
      <filetype>rb</filetype>
      <usage_type>test</usage_type>
      <checksum>63332CE6</checksum>
    </file>
    <file>
      <filename>out.osm</filename>
      <filetype>osm</filetype>
      <usage_type>test</usage_type>
      <checksum>9E6B551B</checksum>
    </file>
    <file>
      <filename>eplusout.sql</filename>
      <filetype>sql</filetype>
      <usage_type>test</usage_type>
      <checksum>EEB234A0</checksum>
    </file>
    <file>
      <filename>cte_lib_reporting.rb</filename>
      <filetype>rb</filetype>
      <usage_type>resource</usage_type>
      <checksum>95F31765</checksum>
    </file>
  </files>
</measure>
